src/d_flip_flop.v
module d_flip_flop(
    input clk,
    input d,
    output reg q
);
    always @(posedge clk) begin
        q <= d;
    end
endmodule

d_flip_flop_tb.v
`timescale 1ns/1ps
module d_flip_flop_tb;
    reg clk = 0;
    reg d;
    wire q;

    d_flip_flop uut(.clk(clk), .d(d), .q(q));

    // generate a clock: flip every 5ns, forever
    always #5 clk = ~clk;

    initial begin
        $dumpfile("dff.vcd");
        $dumpvars(0, d_flip_flop_tb);

        d = 0;
        #12 d = 1;   // change d mid-cycle, not exactly on an edge
        #20 d = 0;
        #20 d = 1;
        #20 $finish;
    end
endmodule

dff.vcd
$date
	Sat Jul 11 16:54:54 2026
$end
$version
	Icarus Verilog
$end
$timescale
	1ps
$end
$scope module d_flip_flop_tb $end
$var wire 1 ! q $end
$var reg 1 " clk $end
$var reg 1 # d $end
$scope module uut $end
$var wire 1 " clk $end
$var wire 1 # d $end
$var reg 1 ! q $end
$upscope $end
$upscope $end
$enddefinitions $end
$comment Show the parameter values. $end
$dumpall
$end
#0
$dumpvars
0#
0"
x!
$end
#5000
0!
1"
#10000
0"
#12000
1#
#15000
1!
1"
#20000
0"
#25000
1"
#30000
0"
#32000
0#
#35000
0!
1"
#40000
0"
#45000
1"
#50000
0"
#52000
1#
#55000
1!
1"
