src/full_adder.v
module full_adder(
    input  a,
    input  b,
    input  cin,
    output sum,
    output cout
);
    assign sum  = a ^ b ^ cin;
    assign cout = (a & b) | (cin & (a ^ b));
endmodule

tb/full_adder_tb.v
`timescale 1ns/1ps
module full_adder_tb;
    reg a, b, cin;
    wire sum, cout;

    full_adder uut(.a(a), .b(b), .cin(cin), .sum(sum), .cout(cout));

    integer i;
    initial begin
        $dumpfile("full_adder.vcd");
        $dumpvars(0, full_adder_tb);
        for (i = 0; i < 8; i = i + 1) begin
            {a, b, cin} = i;
            #10;
            $display("a=%b b=%b cin=%b -> sum=%b cout=%b", a, b, cin, sum, cout);
        end
        $finish;
    end
endmodule

full_adder.vcd
$date
	Sat Jul 04 19:47:52 2026
$end
$version
	Icarus Verilog
$end
$timescale
	1ps
$end
$scope module full_adder_tb $end
$var wire 1 ! sum $end
$var wire 1 " cout $end
$var reg 1 # a $end
$var reg 1 $ b $end
$var reg 1 % cin $end
$var integer 32 & i [31:0] $end
$scope module uut $end
$var wire 1 # a $end
$var wire 1 $ b $end
$var wire 1 % cin $end
$var wire 1 " cout $end
$var wire 1 ! sum $end
$upscope $end
$upscope $end
$enddefinitions $end
$comment Show the parameter values. $end
$dumpall
$end
#0
$dumpvars
b0 &
0%
0$
0#
0"
0!
$end
#10000
1!
1%
b1 &
#20000
1!
1$
0%
b10 &
#30000
1"
0!
1%
b11 &
#40000
0"
1!
1#
0$
0%
b100 &
#50000
1"
0!
1%
b101 &
#60000
0!
1$
0%
b110 &
#70000
1!
1%
b111 &
#80000
b1000 &
