src/register4.v
module register4(
    input        clk,
    input        rst,
    input  [3:0] d,
    output reg [3:0] q
);
    always @(posedge clk) begin
        if (rst)
            q <= 4'b0000;
        else
            q <= d;
    end
endmodule

tb/register4_tb.v
`timescale 1ns/1ps
module register4_tb;
    reg clk = 0;
    reg rst;
    reg [3:0] d;
    wire [3:0] q;

    register4 uut(.clk(clk), .rst(rst), .d(d), .q(q));

    always #5 clk = ~clk;

    initial begin
        $dumpfile("register4.vcd");
        $dumpvars(0, register4_tb);

        rst = 1; d = 0;
        #10 $display("after reset pulse: q=%b (expect 0000)", q);

        rst = 0;
        d = 4'b1010;
        #10 $display("loaded d=1010: q=%b", q);

        d = 4'b0011;
        #10 $display("loaded d=0011: q=%b", q);

        rst = 1;
        #10 $display("reset again mid-run: q=%b (expect 0000)", q);

        $finish;
    end
endmodule

register4.vcd
$date
	Sat Jul 11 17:57:13 2026
$end
$version
	Icarus Verilog
$end
$timescale
	1ps
$end
$scope module register4_tb $end
$var wire 4 ! q [3:0] $end
$var reg 1 " clk $end
$var reg 4 # d [3:0] $end
$var reg 1 $ rst $end
$scope module uut $end
$var wire 1 " clk $end
$var wire 4 % d [3:0] $end
$var wire 1 $ rst $end
$var reg 4 & q [3:0] $end
$upscope $end
$upscope $end
$enddefinitions $end
$comment Show the parameter values. $end
$dumpall
$end
#0
$dumpvars
bx &
b0 %
1$
b0 #
0"
bx !
$end
#5000
b0 !
b0 &
1"
#10000
0"
b1010 #
b1010 %
0$
#15000
b1010 !
b1010 &
1"
#20000
0"
b11 #
b11 %
#25000
b11 !
b11 &
1"
#30000
0"
1$
#35000
b0 !
b0 &
1"
